[
  {
    "id": 1738438420947,
    "title": "# 123",
    "content": "123",
    "audience": [],
    "group": [
      "dfg"
    ],
    "image": "/uploads-announcements/1738443981427_DALL·E 2025-01-13 22.37.13 - A professional logo design with no text, representing a sleek and modern style suitable for a programming studio. The design should focus on innovatio.webp",
    "files": [
      "/uploads-announcements/1738444001029_DALL·E 2025-01-13 22.37.13 - A professional logo design with no text, representing a sleek and modern style suitable for a programming studio. The design should focus on innovatio.webp",
      "/uploads-announcements/1738444001030_DALL·E 2025-01-13 22.35.27 - A redesigned professional logo for 'Phaum Studio', a programming studio. This version should feature a fresh interpretation, focusing on sleek and mod.webp",
      "/uploads-announcements/1738444001031_DALL·E 2025-01-13 21.45.32 - A logo design featuring the name 'Phaum' with the 'U' prominently designed to match the cyberpunk-inspired style. The design uses gray and yellow tone.webp",
      "/uploads-announcements/1738444001037_DALL·E 2025-01-13 21.37.32 - A logo design featuring the name 'Phaum'. The logo should have a futuristic and mystical vibe with gradients of purple and blue as the primary colors.webp"
    ]
  },
  {
    "id": 1739049763088,
    "title": "fsadfgdas",
    "content": "adsfasdfdsa",
    "audience": [
      "teacher",
      "student"
    ],
    "group": [
      "ISTARK"
    ],
    "image": null,
    "files": []
  }
]